<?xml version="1.0" encoding="UTF-8"?>
<feature
      id="org.openscada.external"
      label="openSCADA Externals Feature"
      version="1.0.0.qualifier"
      provider-name="TH4 SYSTEMS GmbH">

   <description>
      This is a wrapper feature for all external bundles which are needed by OpenSCADA.
   </description>

   <copyright>
      See the specific bundle for its copyright information.
   </copyright>

   <license>
      See the specific bundle for its license information.
   </license>

   <includes
         id="org.openscada.external.slf4j"
         version="0.0.0"/>

   <includes
         id="org.openscada.external.spring"
         version="0.0.0"/>

   <requires>
      <import plugin="org.eclipse.osgi"/>
      <import plugin="javax.servlet"/>
   </requires>

   <plugin
         id="org.apache.mina.core"
         download-size="0"
         install-size="0"
         version="0.0.0"
         unpack="false"/>

   <plugin
         id="org.apache.mina.filter.compression"
         download-size="0"
         install-size="0"
         version="0.0.0"
         unpack="false"/>

   <plugin
         id="org.apache.mina.transport.socket.apr"
         download-size="0"
         install-size="0"
         version="0.0.0"
         unpack="false"/>

   <plugin
         id="org.apache.tomcat-apr"
         download-size="0"
         install-size="0"
         version="0.0.0"
         unpack="false"/>

   <plugin
         id="com.springsource.org.apache.xmlbeans"
         download-size="0"
         install-size="0"
         version="0.0.0"
         unpack="false"/>

   <plugin
         id="com.springsource.javax.transaction"
         download-size="0"
         install-size="0"
         version="0.0.0"
         unpack="false"/>

   <plugin
         id="com.springsource.javax.xml.stream"
         download-size="0"
         install-size="0"
         version="0.0.0"
         unpack="false"/>

   <plugin
         id="com.springsource.org.jvnet.staxex"
         download-size="0"
         install-size="0"
         version="0.0.0"
         unpack="false"/>

   <plugin
         id="com.springsource.org.apache.commons.beanutils"
         download-size="0"
         install-size="0"
         version="0.0.0"
         unpack="false"/>

   <plugin
         id="com.springsource.org.apache.commons.collections"
         download-size="0"
         install-size="0"
         version="0.0.0"
         unpack="false"/>

   <plugin
         id="com.springsource.antlr"
         download-size="0"
         install-size="0"
         version="0.0.0"
         unpack="false"/>

   <plugin
         id="com.springsource.org.dom4j"
         download-size="0"
         install-size="0"
         version="0.0.0"
         unpack="false"/>

   <plugin
         id="com.springsource.javassist"
         download-size="0"
         install-size="0"
         version="0.0.0"
         unpack="false"/>

   <plugin
         id="com.springsource.net.sf.cglib"
         download-size="0"
         install-size="0"
         version="0.0.0"
         unpack="false"/>

   <plugin
         id="com.springsource.javax.ejb"
         download-size="0"
         install-size="0"
         version="0.0.0"
         unpack="false"/>

   <plugin
         id="com.springsource.javax.xml.rpc"
         download-size="0"
         install-size="0"
         version="0.0.0"
         unpack="false"/>

   <plugin
         id="com.springsource.javax.activation"
         download-size="0"
         install-size="0"
         version="0.0.0"
         unpack="false"/>

   <plugin
         id="com.springsource.javax.jms"
         download-size="0"
         install-size="0"
         version="0.0.0"
         unpack="false"/>

   <plugin
         id="com.springsource.javax.xml.soap"
         download-size="0"
         install-size="0"
         version="0.0.0"
         unpack="false"/>

   <plugin
         id="com.springsource.org.aopalliance"
         download-size="0"
         install-size="0"
         version="0.0.0"
         unpack="false"/>

   <plugin
         id="com.springsource.org.hsqldb"
         download-size="0"
         install-size="0"
         version="0.0.0"
         unpack="false"/>

   <plugin
         id="com.springsource.javax.jws"
         download-size="0"
         install-size="0"
         version="0.0.0"
         unpack="false"/>

   <plugin
         id="com.springsource.org.antlr"
         download-size="0"
         install-size="0"
         version="0.0.0"
         unpack="false"/>

   <plugin
         id="jackson-core-lgpl"
         download-size="0"
         install-size="0"
         version="0.0.0"
         unpack="false"/>

   <plugin
         id="jackson-mapper-lgpl"
         download-size="0"
         install-size="0"
         version="0.0.0"
         unpack="false"/>

   <plugin
         id="jsr305"
         download-size="0"
         install-size="0"
         version="0.0.0"
         unpack="false"/>

   <plugin
         id="com.google.guava"
         download-size="0"
         install-size="0"
         version="0.0.0"
         unpack="false"/>

   <plugin
         id="org.openscada.external.apache.poi"
         download-size="0"
         install-size="0"
         version="0.0.0"
         unpack="false"/>

   <plugin
         id="com.google.gson"
         download-size="0"
         install-size="0"
         version="0.0.0"
         unpack="false"/>

   <plugin
         id="org.apache.commons.daemon"
         download-size="0"
         install-size="0"
         version="0.0.0"
         unpack="false"/>

   <plugin
         id="org.openscada.external.osgi.enterprise"
         download-size="0"
         install-size="0"
         version="0.0.0"
         unpack="false"/>

   <plugin
         id="jcl.over.slf4j"
         download-size="0"
         install-size="0"
         version="0.0.0"
         unpack="false"/>

   <plugin
         id="log4j.over.slf4j"
         download-size="0"
         install-size="0"
         version="0.0.0"
         unpack="false"/>

   <plugin
         id="jul.to.slf4j"
         download-size="0"
         install-size="0"
         version="0.0.0"
         unpack="false"/>

   <plugin
         id="org.openscada.external.logback.default"
         download-size="0"
         install-size="0"
         version="0.0.0"
         fragment="true"/>

   <plugin
         id="org.openscada.external.postgresql"
         download-size="0"
         install-size="0"
         version="0.0.0"/>

   <plugin
         id="org.apache.commons.dbcp"
         download-size="0"
         install-size="0"
         version="0.0.0"
         unpack="false"/>

   <plugin
         id="org.apache.commons.pool"
         download-size="0"
         install-size="0"
         version="0.0.0"
         unpack="false"/>

   <plugin
         id="org.apache.commons.io"
         download-size="0"
         install-size="0"
         version="0.0.0"
         unpack="false"/>

   <plugin
         id="org.apache.xerces"
         download-size="0"
         install-size="0"
         version="0.0.0"
         unpack="false"/>

   <plugin
         id="org.openscada.external.odfdom"
         download-size="0"
         install-size="0"
         version="0.0.0"
         unpack="false"/>

   <plugin
         id="javax.xml"
         download-size="0"
         install-size="0"
         version="0.0.0"
         unpack="false"/>

   <plugin
         id="org.apache.xml.resolver"
         download-size="0"
         install-size="0"
         version="0.0.0"
         unpack="false"/>

   <plugin
         id="org.apache.xml.serializer"
         download-size="0"
         install-size="0"
         version="0.0.0"
         unpack="false"/>

   <plugin
         id="org.openscada.external.jbzip2"
         download-size="0"
         install-size="0"
         version="0.0.0"/>

   <plugin
         id="org.openscada.external.jcifs"
         download-size="0"
         install-size="0"
         version="0.0.0"
         unpack="false"/>

   <plugin
         id="com.jcraft.jzlib"
         download-size="0"
         install-size="0"
         version="0.0.0"
         unpack="false"/>

</feature>
